orcha/__init__.py
orcha/__main__.py
orcha/bin/__init__.py
orcha/bin/main.py
orcha/exceptions/__init__.py
orcha/exceptions/shutdown.py
orcha/interfaces/__init__.py
orcha/interfaces/message.py
orcha/interfaces/petition.py
orcha/interfaces/service.py
orcha/lib/__init__.py
orcha/lib/manager.py
orcha/lib/processor.py
orcha/plugins/__init__.py
orcha/plugins/base.py
orcha/plugins/embedded/__init__.py
orcha/plugins/embedded/watchdog.py
orcha/plugins/lp.py
orcha/plugins/utils.py
orcha/properties.py
orcha/utils/__init__.py
orcha/utils/autoproxy.py
orcha/utils/cmd.py
orcha/utils/logging_utils.py
orcha/utils/packages.py
orcha-0.2.6.post2.dist-info/LICENSE
orcha-0.2.6.post2.dist-info/WHEEL
orcha-0.2.6.post2.dist-info/METADATA
orcha-0.2.6.post2.dist-info/RECORD
